pytube_client/__init__.py
pytube_client/hello.py
pytube_client-0.1.11.dist-info/LICENSE
pytube_client-0.1.11.dist-info/METADATA
pytube_client-0.1.11.dist-info/WHEEL
pytube_client-0.1.11.dist-info/RECORD
